tag_shadow_aaron_alphabet/__init__.py
tag_shadow_aaron_alphabet/__main__.py
tag_shadow_aaron_alphabet/_conditions.py
tag_shadow_aaron_alphabet/_tasking.py
tag_shadow_aaron_alphabet/utils.py
tag_shadow_aaron_alphabet-0.0.3.dist-info/LICENSE
tag_shadow_aaron_alphabet-0.0.3.dist-info/METADATA
tag_shadow_aaron_alphabet-0.0.3.dist-info/WHEEL
tag_shadow_aaron_alphabet-0.0.3.dist-info/top_level.txt
tag_shadow_aaron_alphabet-0.0.3.dist-info/RECORD
