Metadata-Version: 2.1
Name: tag-shadow-aaron-alphabet
Version: 0.0.3
Summary: Tagging with shadow-files. 
Author-email: Aaron Alphabet <aaron.alphabet@posteo.org>
License: Copyright © 2023 Aaron Alphabet
Classifier: License :: OSI Approved :: MIT License
Classifier: Programming Language :: Python
Classifier: Programming Language :: Python :: 3
Requires-Python: >=3.11
License-File: LICENSE
Requires-Dist: tomli-w (>=1.0.0)
